eotransform_xarray/__init__.py
eotransform_xarray/_version.py
eotransform_xarray/constants.py
eotransform_xarray/functional/__init__.py
eotransform_xarray/functional/decode.py
eotransform_xarray/functional/load_file_dataframe_to_array.py
eotransform_xarray/functional/load_tif.py
eotransform_xarray/functional/stats.py
eotransform_xarray/geometry/__init__.py
eotransform_xarray/geometry/degrees.py
eotransform_xarray/geometry/pixel_transforms.py
eotransform_xarray/geometry/rect_pixel.py
eotransform_xarray/numba_engine/__init__.py
eotransform_xarray/numba_engine/normalize_sig0_to_ref_lia_by_slope.py
eotransform_xarray/sinks/__init__.py
eotransform_xarray/sinks/combine_shards.py
eotransform_xarray/sinks/geo_tiff.py
eotransform_xarray/storage/__init__.py
eotransform_xarray/storage/storage.py
eotransform_xarray/storage/storage_using_zarr.py
eotransform_xarray/transformers/__init__.py
eotransform_xarray/transformers/add_arrays_to_dataset.py
eotransform_xarray/transformers/add_attrs.py
eotransform_xarray/transformers/aggregate_along_dim.py
eotransform_xarray/transformers/apply_to_data_var.py
eotransform_xarray/transformers/batch.py
eotransform_xarray/transformers/decoder.py
eotransform_xarray/transformers/drop_dims.py
eotransform_xarray/transformers/drop_sel.py
eotransform_xarray/transformers/files_to_xarray.py
eotransform_xarray/transformers/masking_where.py
eotransform_xarray/transformers/modify_attrs.py
eotransform_xarray/transformers/normalize_sig0_to_ref_lia_by_slope.py
eotransform_xarray/transformers/random_sample.py
eotransform_xarray/transformers/raster_add_noise.py
eotransform_xarray/transformers/reduce.py
eotransform_xarray/transformers/rename.py
eotransform_xarray/transformers/resample_with_gauss.py
eotransform_xarray/transformers/reshape_by_coords.py
eotransform_xarray/transformers/select_variable.py
eotransform_xarray/transformers/send_dataset_to_stream.py
eotransform_xarray/transformers/squeeze.py
eotransform_xarray/transformers/to_dataset.py
eotransform_xarray-2.5.3.dist-info/METADATA
eotransform_xarray-2.5.3.dist-info/WHEEL
eotransform_xarray-2.5.3.dist-info/top_level.txt
eotransform_xarray-2.5.3.dist-info/RECORD
