Metadata-Version: 2.1
Name: eotransform-xarray
Version: 2.5.3
Summary: Implements transformations on xarray data structures, to be used with eotransform streamed_process.
Home-page: https://github.com/TUW-GEO/eotransform-xarray
Author: TU Wien GEO MRS group
Author-email: remote.sensing@geo.tuwien.ac.at
Platform: any
Classifier: Development Status :: 5 - Production/Stable
Classifier: Intended Audience :: Science/Research
Classifier: License :: OSI Approved :: MIT License
Classifier: Topic :: Scientific/Engineering
Classifier: Topic :: Scientific/Engineering :: GIS
Classifier: Topic :: Software Development :: Libraries
Classifier: Programming Language :: Python :: 3
Classifier: Programming Language :: Python :: 3.8
Classifier: Programming Language :: Python :: 3.9
Classifier: Operating System :: Microsoft :: Windows
Classifier: Operating System :: POSIX
Classifier: Natural Language :: English
Requires-Dist: eotransform >=1.8
Requires-Dist: xarray
Requires-Dist: rioxarray
Requires-Dist: numpy
Requires-Dist: affine
Requires-Dist: more-itertools
Provides-Extra: lazy
Requires-Dist: dask ; extra == 'lazy'
Provides-Extra: noise
Requires-Dist: scikit-image ; extra == 'noise'
Provides-Extra: resample
Requires-Dist: numba ; extra == 'resample'
Requires-Dist: pyresample ; extra == 'resample'
Provides-Extra: storage
Requires-Dist: zarr ; extra == 'storage'
Provides-Extra: test
Requires-Dist: pytest ; extra == 'test'
Requires-Dist: pytest-cov ; extra == 'test'
Requires-Dist: approvaltests ; extra == 'test'
Requires-Dist: pytest-approvaltests-geo ; extra == 'test'
Requires-Dist: psutil ; extra == 'test'
Requires-Dist: eotransform-pandas >=1.0.0 ; extra == 'test'
Requires-Dist: geopathfinder ; extra == 'test'
Requires-Dist: dask ; extra == 'test'
Requires-Dist: scikit-image ; extra == 'test'
Requires-Dist: numba ; extra == 'test'
Requires-Dist: pyresample ; extra == 'test'
Requires-Dist: pyyaml ; extra == 'test'
Requires-Dist: zarr ; extra == 'test'
